requestspr/__init__.py
requestspr-0.0.3.dist-info/LICENSE
requestspr-0.0.3.dist-info/METADATA
requestspr-0.0.3.dist-info/WHEEL
requestspr-0.0.3.dist-info/top_level.txt
requestspr-0.0.3.dist-info/RECORD
