Metadata-Version: 2.1
Name: requestspr
Version: 0.0.3
Summary: 在启动了Clash的情况下，requests发送请求会报错，于是稍微封装了下
License: MIT
Classifier: License :: OSI Approved :: MIT License
License-File: LICENSE
Requires-Dist: requests
